bootstrapping_postgres/__init__.py
bootstrapping_postgres/cli.py
bootstrapping_postgres/download_data.py
bootstrapping_postgres/settings.py
bootstrapping_postgres/stage_data.py
bootstrapping_postgres-0.1.0.dist-info/METADATA
bootstrapping_postgres-0.1.0.dist-info/WHEEL
bootstrapping_postgres-0.1.0.dist-info/entry_points.txt
bootstrapping_postgres-0.1.0.dist-info/top_level.txt
bootstrapping_postgres-0.1.0.dist-info/RECORD
